{
  "$schema": "https://developer.microsoft.com/json-schemas/fabric/item/report/definition/visualContainer/2.4.0/schema.json",
  "name": "65c495f8209983bd30be",
  "position": {
    "x": 0,
    "y": 0.098057335430286607,
    "z": 2000,
    "height": 140.97468329645804,
    "width": 213.21988874644046,
    "tabOrder": 1000
  },
  "visual": {
    "visualType": "actionButton",
    "objects": {
      "icon": [
        {
          "properties": {
            "shapeType": {
              "expr": {
                "Literal": {
                  "Value": "'blank'"
                }
              }
            }
          },
          "selector": {
            "id": "default"
          }
        }
      ],
      "outline": [
        {
          "properties": {
            "show": {
              "expr": {
                "Literal": {
                  "Value": "false"
                }
              }
            }
          }
        }
      ]
    },
    "visualContainerObjects": {
      "visualLink": [
        {
          "properties": {
            "show": {
              "expr": {
                "Literal": {
                  "Value": "true"
                }
              }
            },
            "type": {
              "expr": {
                "Literal": {
                  "Value": "'Bookmark'"
                }
              }
            },
            "bookmark": {
              "expr": {
                "Literal": {
                  "Value": "'1874f104620f5802d340'"
                }
              }
            },
            "tooltip": {
              "expr": {
                "Literal": {
                  "Value": "'See all items that had an Image Count change in the past day (or selected date range).'"
                }
              }
            }
          }
        }
      ]
    },
    "drillFilterOtherVisuals": true
  },
  "parentGroupName": "42a6b1f27e1ec55b6618",
  "howCreated": "InsertVisualButton"
}