{
  "$schema": "https://developer.microsoft.com/json-schemas/fabric/item/report/definition/visualContainer/2.4.0/schema.json",
  "name": "fc1c7a99f7789465b096",
  "position": {
    "x": 306.25,
    "y": 7.5,
    "z": 1000,
    "height": 53.75,
    "width": 782.5,
    "tabOrder": 0
  },
  "visual": {
    "visualType": "textbox",
    "objects": {
      "general": [
        {
          "properties": {
            "paragraphs": [
              {
                "textRuns": [
                  {
                    "value": "STOCK",
                    "textStyle": {
                      "fontWeight": "bold",
                      "fontFamily": "DIN",
                      "fontSize": "18pt"
                    }
                  }
                ],
                "horizontalTextAlignment": "center"
              },
              {
                "textRuns": [
                  {
                    "value": "An overview of today's item stock, and any changes that occurred. Open Filters Panel on left for more filtering options.",
                    "textStyle": {
                      "fontFamily": "DIN",
                      "fontStyle": "italic",
                      "fontSize": "9pt"
                    }
                  }
                ],
                "horizontalTextAlignment": "center"
              }
            ]
          }
        }
      ]
    },
    "visualContainerObjects": {
      "background": [
        {
          "properties": {
            "show": {
              "expr": {
                "Literal": {
                  "Value": "false"
                }
              }
            }
          }
        }
      ]
    },
    "drillFilterOtherVisuals": true
  }
}